{
    "id": "moneybox.ios-colour-asset-exporter",
    "name": "iOS Colour Asset",
    "description": "iOS Colour Asset Exporter",
    "author": "Ashley Henderson",
    "organization": "Moneybox",
    "homepage": "https://www.moneyboxapp.com/",
    "source_dir": "src",
    "version": "1.0",
    "usesBrands": true,
    "config": {
        "sources": "sources.json",
        "output": "output.json",
        "js": "src/js/helpers.js"
    },
    "engines": {
        "pulsar": "1.0.0",
        "supernova": "1.0.0"
    },
    "tags": [
        "Assets",
        "Asset Catalog",
        "iOS"
    ]
}
